[{"_id":"59108afd7b652a30dd4ee0a3","street":"67 Mai Chí Thọ","ward":"An Phú","District":"Quận 2","city":"Hồ Chí Minh","country":"Việt Nam"},{"_id":"59108ba27b652a30dd4ee0be","street":"63-65 Trần Hưng Đạo","ward":"Bến Nghé","District":"Quận 1","city":"Hồ Chí Minh","country":"Việt Nam"},{"_id":"59108bb47b652a30dd4ee0c2","street":"232 Cao Thắng Nối Dài","ward":"Phường 12","District":"Quận 10","city":"Hồ Chí Minh","country":"Việt Nam"},{"_id":"591422503ba94827b8cf7f91","street":"1 Paster","ward":"Bến Nghé","city":"Hồ Chí Minh","__v":0},{"_id":"5914232d3ba94827b8cf7f93","street":"230 Nguyễn Thái Sơn","ward":"Phường 1","city":"Hồ Chí Minh","__v":0,"District":"Quận Gò Vấp","country":"Việt Nam"}]